README.md
setup.py
kukibanshee/__init__.py
kukibanshee/araq.py
kukibanshee/drone.py
kukibanshee/jar.py
kukibanshee/nozdormu.py
kukibanshee/rfc6265.py
kukibanshee/symmtera.py
kukibanshee.egg-info/PKG-INFO
kukibanshee.egg-info/SOURCES.txt
kukibanshee.egg-info/dependency_links.txt
kukibanshee.egg-info/top_level.txt
kukibanshee/Resources/__init__.py
kukibanshee/Resources/public_suffixes.py