Metadata-Version: 1.1
Name: kukibanshee
Version: 0.3.6
Summary: http cookie,rfc6265
Home-page: https://github.com/ihgazni2/kukibanshee
Author: dapeli
Author-email: terryinzaghi@163.com
License: MIT
Platform: UNKNOWN
Classifier: Environment :: Console
Classifier: Environment :: Web Environment
Classifier: Intended Audience :: End Users/Desktop
Classifier: Intended Audience :: Developers
Classifier: Intended Audience :: System Administrators
Classifier: Programming Language :: Python
